{
  "authority": {
    "corpus_identity_authority": false,
    "decision_ref": "aoa-kag:docs/decisions/AOA-KAG-D-0018-tiered-content-addressed-kag-distribution.md",
    "replaceable": true
  },
  "locator_identity": {
    "artifact_kind": "kag_artifact_locator_set",
    "content_digest": "sha256:c13c4767ba32554e91754e8edae3e757b5ab6c3ccc7d4403674c0a81ed641b0a",
    "corpus_digest": "sha256:086eba76e4d8ccd95494f6a7d272d5dd7ef690269b621fd313d10f31f4b97eea",
    "local_id": "locator:repo-local:kag-artifacts",
    "schema_ref": "aoa-kag:schemas/kag-artifact-locator.schema.json"
  },
  "locators": [
    {
      "locator_id": "owner-public-cas",
      "mutable_location": true,
      "object_key_template": "objects/sha256/{prefix}/{digest}",
      "pack_key_template": "packs/sha256/{prefix}/{digest}.pack",
      "priority": 100,
      "transport": "cas",
      "trust_domain": "public-kag"
    }
  ],
  "repo": {
    "git_ref": "git-index-source-tree",
    "name": "aoa-kag",
    "namespace": "aoa:aoa-kag",
    "owner_type": "organ",
    "root": "."
  },
  "schema_version": "aoa-kag-artifact-locator-v1"
}
